{
  "main": {
    "id": "8da334c8d1ba9158",
    "type": "split",
    "children": [
      {
        "id": "38be191f290267ea",
        "type": "tabs",
        "children": [
          {
            "id": "8fbef05b458413d8",
            "type": "leaf",
            "state": {
              "type": "empty",
              "state": {},
              "icon": "lucide-file",
              "title": "New tab"
            }
          }
        ]
      }
    ],
    "direction": "vertical"
  },
  "left": {
    "id": "07449116e2eb1da4",
    "type": "split",
    "children": [
      {
        "id": "7798b8d378b7977d",
        "type": "tabs",
        "children": [
          {
            "id": "df61fdece8ae24f5",
            "type": "leaf",
            "state": {
              "type": "file-explorer",
              "state": {
                "sortOrder": "alphabetical",
                "autoReveal": false
              },
              "icon": "lucide-folder-closed",
              "title": "Files"
            }
          },
          {
            "id": "4306c30eebdb9458",
            "type": "leaf",
            "state": {
              "type": "search",
              "state": {
                "query": "",
                "matchingCase": false,
                "explainSearch": false,
                "collapseAll": false,
                "extraContext": false,
                "sortOrder": "alphabetical"
              },
              "icon": "lucide-search",
              "title": "Search"
            }
          },
          {
            "id": "f5cc80833e7b49bc",
            "type": "leaf",
            "state": {
              "type": "bookmarks",
              "state": {},
              "icon": "lucide-bookmark",
              "title": "Bookmarks"
            }
          }
        ]
      }
    ],
    "direction": "horizontal",
    "width": 300
  },
  "right": {
    "id": "562368bdc063d38b",
    "type": "split",
    "children": [
      {
        "id": "ebffb92346ab7679",
        "type": "tabs",
        "children": [
          {
            "id": "f88bc5744aad5ae6",
            "type": "leaf",
            "state": {
              "type": "backlink",
              "state": {
                "collapseAll": false,
                "extraContext": false,
                "sortOrder": "alphabetical",
                "showSearch": false,
                "searchQuery": "",
                "backlinkCollapsed": false,
                "unlinkedCollapsed": true
              },
              "icon": "links-coming-in",
              "title": "Backlinks"
            }
          },
          {
            "id": "c7906825c6b87556",
            "type": "leaf",
            "state": {
              "type": "outgoing-link",
              "state": {
                "linksCollapsed": false,
                "unlinkedCollapsed": true
              },
              "icon": "links-going-out",
              "title": "Outgoing links"
            }
          },
          {
            "id": "bd91f855caade95c",
            "type": "leaf",
            "state": {
              "type": "tag",
              "state": {
                "sortOrder": "frequency",
                "useHierarchy": true,
                "showSearch": false,
                "searchQuery": ""
              },
              "icon": "lucide-tags",
              "title": "Tags"
            }
          },
          {
            "id": "3df8a963c50b29a8",
            "type": "leaf",
            "state": {
              "type": "outline",
              "state": {
                "followCursor": false,
                "showSearch": false,
                "searchQuery": ""
              },
              "icon": "lucide-list",
              "title": "Outline"
            }
          }
        ]
      }
    ],
    "direction": "horizontal",
    "width": 300,
    "collapsed": true
  },
  "left-ribbon": {
    "hiddenItems": {
      "switcher:Open quick switcher": false,
      "graph:Open graph view": false,
      "canvas:Create new canvas": false,
      "daily-notes:Open today's daily note": false,
      "templates:Insert template": false,
      "command-palette:Open command palette": false,
      "bases:Create new base": false
    }
  },
  "active": "8fbef05b458413d8",
  "lastOpenFiles": [
    "vts-terminal/intro.md.tmp.1631404.1759686683009",
    "psd-layer-animation/intro.md",
    "psd-layer-animation/intro.md.tmp.1631404.1759686579075",
    "psd-layer-animation",
    "live2d-physics/intro.md",
    "live2d-physics/intro.md.tmp.1631404.1759686024559",
    "vts-terminal/intro.md",
    "vts-terminal/intro.md.tmp.1631404.1759686018954",
    "live2d-physics",
    "vts-terminal",
    "tutorial-basics/congratulations.md",
    "tutorial-basics/create-a-document.md",
    "tutorial-basics/deploy-your-site.md",
    "tutorial-basics/create-a-page.md",
    "tutorial-extras/translate-your-site.md",
    "tutorial-extras/manage-docs-versions.md"
  ]
}